claude_stateless_agent/__init__.py
claude_stateless_agent-0.0.1.dist-info/METADATA
claude_stateless_agent-0.0.1.dist-info/WHEEL
claude_stateless_agent-0.0.1.dist-info/RECORD
