Metadata-Version: 2.4
Name: claude_stateless_agent
Version: 0.0.1
Summary: Hooks-only, stateless Claude Agent helpers.
Project-URL: Homepage, https://github.com/dhruvbaldawa/claude-stateless-agent-python
Author: Dhruv Baldawa
Requires-Python: >=3.8
